abstract_scorm_xblock/__init__.py
abstract_scorm_xblock/app.py
abstract_scorm_xblock/constants.py
abstract_scorm_xblock/exceptions.py
abstract_scorm_xblock/scormxblock.py
abstract_scorm_xblock/tests.py
abstract_scorm_xblock/utils.py
abstract_scorm_xblock/views.py
abstract_scorm_xblock/locale/es_419/LC_MESSAGES/django.mo
abstract_scorm_xblock/locale/es_419/LC_MESSAGES/django.po
abstract_scorm_xblock/locale/pl/LC_MESSAGES/text.po
abstract_scorm_xblock/static/README.txt
abstract_scorm_xblock/static/css/scormxblock.css
abstract_scorm_xblock/static/html/scormxblock.html
abstract_scorm_xblock/static/html/studio.html
abstract_scorm_xblock/static/js/src/scormxblock.js
abstract_scorm_xblock/static/js/src/studio.js
abstract_scorm_xblock-1.0.1.dist-info/METADATA
abstract_scorm_xblock-1.0.1.dist-info/WHEEL
abstract_scorm_xblock-1.0.1.dist-info/entry_points.txt
abstract_scorm_xblock-1.0.1.dist-info/top_level.txt
abstract_scorm_xblock-1.0.1.dist-info/RECORD
