Metadata-Version: 2.1
Name: abstract-scorm-xblock
Version: 1.0.1
Summary: Load SCORM packages into Open edX courses
Home-page: https://github.com/Abstract-Tech/abstract-scorm-xblock
Author: Alexander Marenich, Andrey Kryachko, Andrey Lykhoman, COTOHA, David Baumgold, Volodymyr Bergman, Maxim Starodubcev, Jorge Mora, Silvio Tomatis, kirkerafael, Oksana Slusarenro, Chiruzzi Marco
Author-email: sendr84@gmail.com, andrey.kryachko@raccoongang.com, andrey.likhoman@gmail.com, sergiy.movchan@gmail.com, david@davidbaumgold.com, wowkalucky@gmail.com, starodubcevmax@gmail.com, jorge.mora@innovapues.com, silviot@gmail.com, kirkerafael@gmail.com, oksana.slu@gmail.com, chiruzzi.marco@gmail.com
Maintainer: Silvio Tomatis, Chiruzzi Marco
Maintainer-email: silviot@gmail.com, chiruzzi.marco@gmail.com
License: Apache 2.0
Download-URL: https://github.com/Abstract-Tech/abstract-scorm-xblock/archive/v1.0.0.tar.gz
Keywords: scorm,xblock
Platform: UNKNOWN
Classifier: Development Status :: 5 - Production/Stable
Classifier: Intended Audience :: Developers
Classifier: License :: OSI Approved :: Apache Software License
Classifier: Natural Language :: English
Classifier: Programming Language :: Python :: 2.7
Classifier: Framework :: Django
Classifier: License :: OSI Approved :: Apache Software License
Requires-Dist: XBlock
